md_dead_link_check/__main__.py
md_dead_link_check/config.py
md_dead_link_check/helpers.py
md_dead_link_check/link_checker.py
md_dead_link_check/preprocess.py
md_dead_link_check-1.1.0.dist-info/METADATA
md_dead_link_check-1.1.0.dist-info/WHEEL
md_dead_link_check-1.1.0.dist-info/entry_points.txt
md_dead_link_check-1.1.0.dist-info/licenses/LICENSE
md_dead_link_check-1.1.0.dist-info/RECORD
