Metadata-Version: 2.4
Name: md_dead_link_check
Version: 1.1.0
Summary: This is a lightweight and fast tool to help you keep your Markdown files free of broken links.
Project-URL: Repository, https://github.com/AlexanderDokuchaev/md-dead-link-check
Project-URL: Issues, https://github.com/AlexanderDokuchaev/md-dead-link-check/issues
License: MIT
License-File: LICENSE
Keywords: broken link,broken link checker,dead link,dead link checker,documentation maintenance,link checker,link health,markdown
Classifier: Development Status :: 4 - Beta
Classifier: Intended Audience :: Developers
Classifier: License :: OSI Approved :: Apache Software License
Classifier: Operating System :: OS Independent
Classifier: Programming Language :: Python :: 3.9
Classifier: Programming Language :: Python :: 3.10
Classifier: Programming Language :: Python :: 3.11
Classifier: Programming Language :: Python :: 3.12
Requires-Python: >=3.9
Requires-Dist: aiohttp<3.12.0,>=3.10.11
Requires-Dist: gitpython<3.2.0,>=3.1.0
Requires-Dist: toml<3.11.0,>=0.7.0
Provides-Extra: dev
Requires-Dist: pre-commit==3.2.2; extra == 'dev'
Requires-Dist: pytest==7.4.3; extra == 'dev'
Provides-Extra: lint
Requires-Dist: black==24.2.0; extra == 'lint'
Requires-Dist: isort==5.13.2; extra == 'lint'
